{"is_source_file": true, "format": "JavaScript", "description": "This file defines user management functions in a Node.js project, including user creation, authentication, and retrieval by ID or username, using a JSON file as storage and bcrypt for password hashing.", "external_files": ["bcrypt", "fs", "path"], "external_methods": ["bcrypt.hash", "bcrypt.compare"], "published": ["createUser", "authenticate", "getUserById", "getUserByUsername"], "classes": [], "methods": [{"name": "createUser({ username, password })", "description": "Creates a new user with a hashed password and stores it in the JSON database.", "scope": "", "scopeKind": ""}, {"name": "authenticate(username, password)", "description": "Validates user credentials by comparing the provided password with the stored hashed password.", "scope": "", "scopeKind": ""}, {"name": "getUserById(id)", "description": "Retrieves user details based on the user ID.", "scope": "", "scopeKind": ""}, {"name": "getUserByUsername(username)", "description": "Retrieves user details based on the username.", "scope": "", "scopeKind": ""}, {"name": "readUsers()", "scope": "", "scopeKind": "", "description": "unavailable"}, {"name": "writeUsers(users)", "scope": "", "scopeKind": "", "description": "unavailable"}], "calls": ["bcrypt.hash", "bcrypt.compare", "readUsers", "writeUsers"], "search-terms": ["user management", "auth", "bcrypt", "json database", "user creation", "login"], "state": 2, "file_id": 13, "knowledge_revision": 27, "git_revision": "", "ctags": [{"_type": "tag", "name": "DB_PATH", "path": "/home/kavia/workspace/code-generation/note-keeper-5882-5891/notes_backend/src/models/user.js", "pattern": "/^const DB_PATH = process.env.NOTES_DB_PATH || '.\\/data\\/users.json';$/", "language": "JavaScript", "kind": "constant"}, {"_type": "tag", "name": "authenticate", "path": "/home/kavia/workspace/code-generation/note-keeper-5882-5891/notes_backend/src/models/user.js", "pattern": "/^async function authenticate(username, password) {$/", "language": "JavaScript", "kind": "function", "signature": "(username, password)"}, {"_type": "tag", "name": "bcrypt", "path": "/home/kavia/workspace/code-generation/note-keeper-5882-5891/notes_backend/src/models/user.js", "pattern": "/^const bcrypt = require('bcrypt');$/", "language": "JavaScript", "kind": "constant"}, {"_type": "tag", "name": "createUser", "path": "/home/kavia/workspace/code-generation/note-keeper-5882-5891/notes_backend/src/models/user.js", "pattern": "/^async function createUser({ username, password }) {$/", "language": "JavaScript", "kind": "function", "signature": "({ username, password })"}, {"_type": "tag", "name": "createUser", "path": "/home/kavia/workspace/code-generation/note-keeper-5882-5891/notes_backend/src/models/user.js", "pattern": "/^module.exports = { createUser, authenticate, getUserById, getUserByUsername };$/", "language": "JavaScript", "kind": "field", "scope": "module.exports", "scopeKind": "class"}, {"_type": "tag", "name": "dbFile", "path": "/home/kavia/workspace/code-generation/note-keeper-5882-5891/notes_backend/src/models/user.js", "pattern": "/^const dbFile = path.resolve(DB_PATH);$/", "language": "JavaScript", "kind": "constant"}, {"_type": "tag", "name": "fs", "path": "/home/kavia/workspace/code-generation/note-keeper-5882-5891/notes_backend/src/models/user.js", "pattern": "/^const fs = require('fs');$/", "language": "JavaScript", "kind": "constant"}, {"_type": "tag", "name": "getUserById", "path": "/home/kavia/workspace/code-generation/note-keeper-5882-5891/notes_backend/src/models/user.js", "pattern": "/^function getUserById(id) {$/", "language": "JavaScript", "kind": "function", "signature": "(id)"}, {"_type": "tag", "name": "getUserByUsername", "path": "/home/kavia/workspace/code-generation/note-keeper-5882-5891/notes_backend/src/models/user.js", "pattern": "/^function getUserByUsername(username) {$/", "language": "JavaScript", "kind": "function", "signature": "(username)"}, {"_type": "tag", "name": "id", "path": "/home/kavia/workspace/code-generation/note-keeper-5882-5891/notes_backend/src/models/user.js", "pattern": "/^  const user = { id: Date.now().toString(), username, password: hashed };$/", "language": "JavaScript", "kind": "property", "scope": "createUser.user", "scopeKind": "class"}, {"_type": "tag", "name": "path", "path": "/home/kavia/workspace/code-generation/note-keeper-5882-5891/notes_backend/src/models/user.js", "pattern": "/^const path = require('path');$/", "language": "JavaScript", "kind": "constant"}, {"_type": "tag", "name": "readUsers", "path": "/home/kavia/workspace/code-generation/note-keeper-5882-5891/notes_backend/src/models/user.js", "pattern": "/^function readUsers() {$/", "language": "JavaScript", "kind": "function", "signature": "()"}, {"_type": "tag", "name": "user", "path": "/home/kavia/workspace/code-generation/note-keeper-5882-5891/notes_backend/src/models/user.js", "pattern": "/^  const user = { id: Date.now().toString(), username, password: hashed };$/", "language": "JavaScript", "kind": "class", "scope": "createUser", "scopeKind": "class"}, {"_type": "tag", "name": "username", "path": "/home/kavia/workspace/code-generation/note-keeper-5882-5891/notes_backend/src/models/user.js", "pattern": "/^  const user = { id: Date.now().toString(), username, password: hashed };$/", "language": "JavaScript", "kind": "field", "scope": "createUser.user", "scopeKind": "class"}, {"_type": "tag", "name": "writeUsers", "path": "/home/kavia/workspace/code-generation/note-keeper-5882-5891/notes_backend/src/models/user.js", "pattern": "/^function writeUsers(users) {$/", "language": "JavaScript", "kind": "function", "signature": "(users)"}], "hash": "f9f89f3991d57780d9e3b5cf3454f53d", "format-version": 4, "code-base-name": "notes_backend", "filename": "notes_backend/src/models/user.js", "fields": [{"name": "module.exports = { createUser, authenticate, getUserById, getUserByUsername };", "scope": "module.exports", "scopeKind": "class", "description": "unavailable"}, {"name": "const user = { id: Date.now().toString(), username, password: hashed };", "scope": "createUser.user", "scopeKind": "class", "description": "unavailable"}], "revision_history": [{"27": ""}]}